whylabs_client/__init__.py
whylabs_client/api_client.py
whylabs_client/configuration.py
whylabs_client/exceptions.py
whylabs_client/model_utils.py
whylabs_client/rest.py
whylabs_client/api/__init__.py
whylabs_client/api/api_key_api.py
whylabs_client/api/assets_api.py
whylabs_client/api/audit_logs_api.py
whylabs_client/api/data_api.py
whylabs_client/api/dataset_metadata_api.py
whylabs_client/api/dataset_profile_api.py
whylabs_client/api/debug_events_api.py
whylabs_client/api/diagnostics_api.py
whylabs_client/api/events_api.py
whylabs_client/api/feature_weights_api.py
whylabs_client/api/log_api.py
whylabs_client/api/membership_api.py
whylabs_client/api/models_api.py
whylabs_client/api/monitor_api.py
whylabs_client/api/monitor_diagnostics_api.py
whylabs_client/api/notification_settings_api.py
whylabs_client/api/organizations_api.py
whylabs_client/api/policy_api.py
whylabs_client/api/schema_api.py
whylabs_client/api/security_api.py
whylabs_client/api/sessions_api.py
whylabs_client/api/traces_api.py
whylabs_client/api/transactions_api.py
whylabs_client/apis/__init__.py
whylabs_client/model/__init__.py
whylabs_client/model/account_organization.py
whylabs_client/model/account_user.py
whylabs_client/model/acknowledge_notification_request.py
whylabs_client/model/action_type.py
whylabs_client/model/add_membership_request.py
whylabs_client/model/add_policy_response.py
whylabs_client/model/admin_report_response.py
whylabs_client/model/admin_report_type.py
whylabs_client/model/analysis_results_record.py
whylabs_client/model/analysis_results_request.py
whylabs_client/model/analysis_results_response.py
whylabs_client/model/analysis_results_summary.py
whylabs_client/model/analyzer_diagnostic_record.py
whylabs_client/model/analyzer_failure_record.py
whylabs_client/model/analyzer_segment_column_diagnostic_record.py
whylabs_client/model/analyzer_segment_columns_diagnostic_request.py
whylabs_client/model/analyzer_segment_columns_diagnostic_response.py
whylabs_client-0.6.16.dist-info/METADATA
whylabs_client-0.6.16.dist-info/WHEEL
whylabs_client-0.6.16.dist-info/top_level.txt
whylabs_client-0.6.16.dist-info/RECORD
