Metadata-Version: 2.1
Name: whylabs-client
Version: 0.6.16
Summary: WhyLabs API client
Home-page: UNKNOWN
Author: WhyLabs
Author-email: support@whylabs.ai
License: Apache License 2.0
Keywords: OpenAPI,OpenAPI-Generator,WhyLabs API client
Platform: UNKNOWN
Requires-Python: >=3.6
Requires-Dist: urllib3 (>=1.25.3)
Requires-Dist: python-dateutil
